vertexai_ray_job_af_trigger/__init__.py
vertexai_ray_job_af_trigger/ray_job_trigger.py
vertexai_ray_job_af_trigger-0.0.4.dist-info/LICENSE
vertexai_ray_job_af_trigger-0.0.4.dist-info/METADATA
vertexai_ray_job_af_trigger-0.0.4.dist-info/WHEEL
vertexai_ray_job_af_trigger-0.0.4.dist-info/top_level.txt
vertexai_ray_job_af_trigger-0.0.4.dist-info/RECORD
